README.rst
setup.cfg
setup.py
cdp/__init__.py
cdp/__main__.py
cdp/cdp.py
cdp.egg-info/PKG-INFO
cdp.egg-info/SOURCES.txt
cdp.egg-info/dependency_links.txt
cdp.egg-info/entry_points.txt
cdp.egg-info/not-zip-safe
cdp.egg-info/requires.txt
cdp.egg-info/top_level.txt