Metadata-Version: 1.0
Name: cdp
Version: 0.0.2
Summary: Change Directory Plus
Home-page: https://github.com/kootenpv/yagmail
Author: Pascal van Kooten
Author-email: kootenpv@gmail.com
License: GPL
Platform: UNKNOWN
